<?xml version="1.0" encoding="utf-8"?>
<db version="3" seq_piece="34020">
  <pieces>
    <piece id="297">
      <classement>
        <version date="22/11/2016 16:52:35" value="0002110.2" />
      </classement>
      <disabled />
    </piece>
    <piece id="863">
      <classement>
        <version date="22/11/2016 19:08:14" value="0012.2" />
      </classement>
    </piece>
    <piece id="21829" parent="863">
      <duration>273198</duration>
    </piece>
    <piece id="1971">
      <classement>
        <version date="22/11/2016 14:37:33" value="0010.0" />
      </classement>
    </piece>
    <piece id="2457">
      <classement>
        <version date="22/11/2016 10:34:59" value="0015.0" />
      </classement>
    </piece>
    <piece id="2910">
      <classement>
        <version date="22/11/2016 10:37:26" value="0015.5" />
      </classement>
    </piece>
    <piece id="2946">
      <classement>
        <version date="22/11/2016 14:30:22" value="0010.3" />
      </classement>
    </piece>
    <piece id="3270">
      <classement>
        <version date="22/11/2016 16:47:06" value="0010.4" />
      </classement>
      <duration>229078</duration>
    </piece>
    <piece id="4809">
      <classement>
        <version date="22/11/2016 14:34:29" value="0005.5" />
      </classement>
    </piece>
    <piece id="5958">
      <classement>
        <version date="22/11/2016 17:53:38" value="0010.0" />
      </classement>
    </piece>
    <piece id="6302">
      <classement>
        <version date="22/11/2016 15:17:06" value="0010.0" />
      </classement>
    </piece>
    <piece id="6406">
      <classement>
        <version date="22/11/2016 11:20:02" value="0005332.0" />
      </classement>
      <disabled />
    </piece>
    <piece id="6643">
      <duration>333957</duration>
    </piece>
    <piece id="6644">
      <classement>
        <version date="22/11/2016 18:01:11" value="00054.2" />
      </classement>
    </piece>
    <piece id="6647">
      <classement>
        <version date="22/11/2016 10:22:20" value="0005.3" />
      </classement>
    </piece>
    <piece id="6669">
      <classement>
        <version date="22/11/2016 11:20:51" value="0005.3" />
      </classement>
    </piece>
    <piece id="6670">
      <classement>
        <version date="22/11/2016 15:20:52" value="0010.2" />
      </classement>
    </piece>
    <piece id="7167">
      <classement>
        <version date="22/11/2016 13:56:40" value="0025.1" />
      </classement>
      <duration>413571</duration>
    </piece>
    <piece id="7425">
      <classement>
        <version date="22/11/2016 18:12:52" value="0005.4" />
      </classement>
      <duration>203234</duration>
    </piece>
    <piece id="8169">
      <classement>
        <version date="22/11/2016 16:50:35" value="0005252.3" />
      </classement>
      <disabled />
      <duration>246471</duration>
    </piece>
    <piece id="8219">
      <classement>
        <version date="22/11/2016 14:20:38" value="0005.4" />
      </classement>
    </piece>
    <piece id="8257">
      <classement>
        <version date="22/11/2016 11:04:22" value="0005.3" />
      </classement>
    </piece>
    <piece id="8260">
      <classement>
        <version date="22/11/2016 14:42:48" value="0005.4" />
      </classement>
      <duration>394136</duration>
    </piece>
    <piece id="9368">
      <classement>
        <version date="22/11/2016 10:50:46" value="0005.4" />
      </classement>
      <duration>240980</duration>
    </piece>
    <piece id="9532">
      <classement>
        <version date="22/11/2016 14:26:24" value="0010.4" />
      </classement>
    </piece>
    <piece id="10163">
      <classement>
        <version date="22/11/2016 14:25:54" value="0005.3" />
      </classement>
    </piece>
    <piece id="10276">
      <classement>
        <version date="22/11/2016 14:40:36" value="0014.3" />
      </classement>
    </piece>
    <piece id="11176">
      <dates>
        <date>22/11/2016 19:13:37</date>
      </dates>
      <duration>206267</duration>
    </piece>
    <piece id="11177">
      <duration>174707</duration>
    </piece>
    <piece id="12543">
      <classement>
        <version date="22/11/2016 16:10:27" value="0103.4" />
      </classement>
      <dates>
        <date>22/11/2016 16:07:16</date>
      </dates>
      <duration>249933</duration>
    </piece>
    <piece id="12756">
      <classement>
        <version date="22/11/2016 10:25:27" value="0011.5" />
      </classement>
    </piece>
    <piece id="12890">
      <classement>
        <version date="22/11/2016 10:59:55" value="0020.2" />
      </classement>
    </piece>
    <piece id="14683">
      <classement>
        <version date="22/11/2016 17:48:12" value="0010.0" />
      </classement>
    </piece>
    <piece id="14684">
      <classement>
        <version date="22/11/2016 11:00:43" value="0005.5" />
      </classement>
    </piece>
    <piece id="14808">
      <classement>
        <version date="22/11/2016 13:41:24" value="0011.0" />
      </classement>
    </piece>
    <piece id="14817">
      <classement>
        <version date="22/11/2016 18:51:37" value="0131.3" />
      </classement>
    </piece>
    <piece id="15153">
      <classement>
        <version date="22/11/2016 14:44:27" value="0010.1" />
      </classement>
    </piece>
    <piece id="15264">
      <classement>
        <version date="22/11/2016 17:23:19" value="0005131.1" />
      </classement>
      <disabled />
      <duration>555773</duration>
    </piece>
    <piece id="15295">
      <classement>
        <version date="22/11/2016 13:49:15" value="0022.1" />
      </classement>
    </piece>
    <piece id="15547">
      <classement>
        <version date="22/11/2016 18:15:39" value="0024.5" />
      </classement>
      <duration>302267</duration>
    </piece>
    <piece id="15744">
      <classement>
        <version date="22/11/2016 12:04:55" value="0011.2" />
      </classement>
    </piece>
    <piece id="15817">
      <classement>
        <version date="22/11/2016 17:11:30" value="0005.4" />
      </classement>
    </piece>
    <piece id="15855">
      <classement>
        <version date="22/11/2016 16:58:03" value="0010.5" />
      </classement>
    </piece>
    <piece id="16162">
      <classement>
        <version date="22/11/2016 16:31:28" value="0010.5" />
      </classement>
    </piece>
    <piece id="16177">
      <classement>
        <version date="22/11/2016 16:39:49" value="00054.3" />
      </classement>
    </piece>
    <piece id="16230">
      <classement>
        <version date="22/11/2016 10:53:14" value="0011.1" />
      </classement>
    </piece>
    <piece id="16254">
      <classement>
        <version date="22/11/2016 17:15:14" value="0034.5" />
      </classement>
    </piece>
    <piece id="16258">
      <classement>
        <version date="22/11/2016 11:15:37" value="0005322.0" />
      </classement>
      <disabled />
    </piece>
    <piece id="16276">
      <classement>
        <version date="22/11/2016 11:18:06" value="00054.2" />
      </classement>
    </piece>
    <piece id="16277">
      <classement>
        <version date="22/11/2016 14:41:52" value="0010.3" />
      </classement>
    </piece>
    <piece id="16504">
      <classement>
        <version date="22/11/2016 16:55:51" value="0005203.1" />
      </classement>
      <disabled />
    </piece>
    <piece id="16505">
      <classement>
        <version date="22/11/2016 17:54:55" value="0013.2" />
      </classement>
    </piece>
    <piece id="16629">
      <classement>
        <version date="22/11/2016 11:11:46" value="0005.4" />
      </classement>
    </piece>
    <piece id="16687">
      <classement>
        <version date="22/11/2016 15:28:28" value="0005.3" />
      </classement>
    </piece>
    <piece id="16814">
      <classement>
        <version date="22/11/2016 12:00:01" value="0010.0" />
      </classement>
    </piece>
    <piece id="17018">
      <classement>
        <version date="22/11/2016 16:02:59" value="0005313.3" />
      </classement>
      <disabled />
    </piece>
    <piece id="17237">
      <classement>
        <version date="22/11/2016 11:43:18" value="00053.2" />
      </classement>
    </piece>
    <piece id="17959">
      <classement>
        <version date="22/11/2016 14:27:29" value="0005.3" />
      </classement>
    </piece>
    <piece id="18076">
      <classement>
        <version date="22/11/2016 15:27:15" value="0005.3" />
      </classement>
    </piece>
    <piece id="18136">
      <classement>
        <version date="22/11/2016 13:25:23" value="0005351.0" />
      </classement>
      <disabled />
    </piece>
    <piece id="18368">
      <classement>
        <version date="22/11/2016 16:48:40" value="0004244.1" />
      </classement>
      <disabled />
    </piece>
    <piece id="18422">
      <classement>
        <version date="22/11/2016 11:10:14" value="0005.4" />
      </classement>
    </piece>
    <piece id="18476">
      <classement>
        <version date="22/11/2016 14:36:03" value="0005.5" />
      </classement>
    </piece>
    <piece id="18518">
      <classement>
        <version date="22/11/2016 14:52:10" value="0011.0" />
      </classement>
      <dates>
        <date>22/11/2016 14:51:35</date>
      </dates>
    </piece>
    <piece id="18522">
      <classement>
        <version date="22/11/2016 14:19:07" value="0005.5" />
      </classement>
    </piece>
    <piece id="18558">
      <classement>
        <version date="22/11/2016 16:43:23" value="0011.3" />
      </classement>
      <dates>
        <date>22/11/2016 16:43:28</date>
      </dates>
    </piece>
    <piece id="18960">
      <classement>
        <version date="22/11/2016 18:17:59" value="0005255.1" />
      </classement>
      <disabled />
    </piece>
    <piece id="19218">
      <classement>
        <version date="22/11/2016 11:52:22" value="0005.4" />
      </classement>
    </piece>
    <piece id="19220">
      <classement>
        <version date="22/11/2016 17:59:04" value="0005302.1" />
      </classement>
      <disabled />
    </piece>
    <piece id="19357">
      <classement>
        <version date="22/11/2016 14:46:46" value="0124.1" />
      </classement>
    </piece>
    <piece id="19428">
      <classement>
        <version date="22/11/2016 17:38:12" value="0005.4" />
      </classement>
    </piece>
    <piece id="19429">
      <classement>
        <version date="22/11/2016 18:40:31" value="0010.1" />
      </classement>
      <dates>
        <date>22/11/2016 18:38:08</date>
      </dates>
    </piece>
    <piece id="19490">
      <classement>
        <version date="22/11/2016 13:52:24" value="0005245.3" />
      </classement>
      <disabled />
    </piece>
    <piece id="19510">
      <classement>
        <version date="22/11/2016 13:43:36" value="0012.0" />
      </classement>
    </piece>
    <piece id="19559">
      <classement>
        <version date="22/11/2016 15:13:21" value="0012.0" />
      </classement>
      <disabled />
    </piece>
    <piece id="19616">
      <classement>
        <version date="22/11/2016 13:40:34" value="0010.5" />
      </classement>
    </piece>
    <piece id="19728">
      <classement>
        <version date="22/11/2016 18:22:09" value="0010.4" />
      </classement>
    </piece>
    <piece id="19730">
      <classement>
        <version date="22/11/2016 13:50:39" value="00055.1" />
      </classement>
    </piece>
    <piece id="19743">
      <classement>
        <version date="22/11/2016 11:45:04" value="0005223.1" />
      </classement>
      <disabled />
    </piece>
    <piece id="19810">
      <classement>
        <version date="22/11/2016 15:18:04" value="0005303.3" />
      </classement>
      <disabled />
    </piece>
    <piece id="19936">
      <classement>
        <version date="22/11/2016 12:01:22" value="0015.0" />
      </classement>
    </piece>
    <piece id="19995">
      <classement>
        <version date="22/11/2016 10:48:22" value="0044.4" />
      </classement>
    </piece>
    <piece id="20031">
      <classement>
        <version date="22/11/2016 16:58:59" value="0005.3" />
      </classement>
    </piece>
    <piece id="20032">
      <classement>
        <version date="22/11/2016 18:02:44" value="0015.1" />
      </classement>
    </piece>
    <piece id="20076">
      <classement>
        <version date="22/11/2016 19:02:35" value="0015.5" />
      </classement>
    </piece>
    <piece id="20265">
      <classement>
        <version date="22/11/2016 16:01:53" value="0011.1" />
      </classement>
    </piece>
    <piece id="20300">
      <classement>
        <version date="22/11/2016 15:25:59" value="0024.1" />
      </classement>
    </piece>
    <piece id="20581">
      <classement>
        <version date="22/11/2016 18:31:28" value="0005341.0" />
      </classement>
      <dates>
        <date>22/11/2016 18:25:38</date>
      </dates>
      <disabled />
    </piece>
    <piece id="20587">
      <classement>
        <version date="22/11/2016 14:58:57" value="0005254.3" />
      </classement>
      <disabled />
    </piece>
    <piece id="20598">
      <classement>
        <version date="22/11/2016 17:35:06" value="0005335.0" />
      </classement>
      <dates>
        <date>22/11/2016 17:34:34</date>
      </dates>
      <disabled />
    </piece>
    <piece id="20720">
      <classement>
        <version date="22/11/2016 17:09:59" value="0002050.4" />
      </classement>
      <disabled />
    </piece>
    <piece id="20721">
      <classement>
        <version date="22/11/2016 18:11:05" value="0015.3" />
      </classement>
    </piece>
    <piece id="21137">
      <classement>
        <version date="22/11/2016 10:56:48" value="0005250.1" />
      </classement>
      <disabled />
    </piece>
    <piece id="21578">
      <classement>
        <version date="22/11/2016 17:19:01" value="0011.0" />
      </classement>
    </piece>
    <piece id="21635">
      <classement>
        <version date="22/11/2016 17:07:46" value="00053.1" />
      </classement>
      <dates>
        <date>22/11/2016 17:06:21</date>
      </dates>
    </piece>
    <piece id="21905">
      <classement>
        <version date="22/11/2016 13:37:13" value="0010.2" />
      </classement>
    </piece>
    <piece id="21912">
      <classement>
        <version date="22/11/2016 14:31:45" value="0010.3" />
      </classement>
    </piece>
    <piece id="22086">
      <classement>
        <version date="22/11/2016 11:38:27" value="0005.3" />
      </classement>
    </piece>
    <piece id="22263">
      <classement>
        <version date="22/11/2016 13:58:16" value="0005310.1" />
      </classement>
      <disabled />
    </piece>
    <piece id="22278">
      <classement>
        <version date="22/11/2016 14:22:28" value="00054.1" />
      </classement>
    </piece>
    <piece id="22468">
      <classement>
        <version date="22/11/2016 11:39:42" value="0020.3" />
      </classement>
    </piece>
    <piece id="22471">
      <classement>
        <version date="22/11/2016 13:46:08" value="00054.2" />
      </classement>
    </piece>
    <piece id="22472">
      <classement>
        <version date="22/11/2016 10:43:05" value="0011.5" />
      </classement>
    </piece>
    <piece id="22611">
      <classement>
        <version date="22/11/2016 17:41:44" value="0005240.2" />
      </classement>
      <disabled />
    </piece>
    <piece id="22613">
      <classement>
        <version date="22/11/2016 15:24:25" value="0005102.2" />
      </classement>
      <disabled />
    </piece>
    <piece id="22638">
      <classement>
        <version date="22/11/2016 13:35:43" value="00053.1" />
      </classement>
    </piece>
    <piece id="22731">
      <classement>
        <version date="22/11/2016 10:36:06" value="0005.5" />
      </classement>
    </piece>
    <piece id="22959">
      <classement>
        <version date="22/11/2016 10:32:58" value="0005.5" />
      </classement>
    </piece>
    <piece id="22992">
      <classement>
        <version date="22/11/2016 11:51:18" value="00055.1" />
      </classement>
    </piece>
    <piece id="23389">
      <classement>
        <version date="22/11/2016 10:57:41" value="00055.3" />
      </classement>
    </piece>
    <piece id="23396">
      <classement>
        <version date="22/11/2016 11:08:52" value="0010.1" />
      </classement>
      <duration>234998</duration>
    </piece>
    <piece id="23405">
      <classement>
        <version date="22/11/2016 16:38:44" value="0004543.1" />
      </classement>
      <disabled />
    </piece>
    <piece id="23514">
      <classement>
        <version date="22/11/2016 18:13:54" value="0011.1" />
      </classement>
    </piece>
    <piece id="23521">
      <classement>
        <version date="22/11/2016 11:41:54" value="00053.3" />
      </classement>
    </piece>
    <piece id="23534">
      <classement>
        <version date="22/11/2016 19:06:41" value="00053.3" />
      </classement>
      <dates>
        <date>22/11/2016 19:06:09</date>
      </dates>
    </piece>
    <piece id="23540">
      <classement>
        <version date="22/11/2016 16:42:24" value="0010.1" />
      </classement>
    </piece>
    <piece id="23564">
      <classement>
        <version date="22/11/2016 11:06:08" value="0003020.4" />
      </classement>
      <disabled />
    </piece>
    <piece id="23576">
      <classement>
        <version date="22/11/2016 18:45:52" value="0005.5" />
      </classement>
      <dates>
        <date>22/11/2016 18:44:32</date>
      </dates>
    </piece>
    <piece id="23700">
      <classement>
        <version date="22/11/2016 17:46:50" value="00053.5" />
      </classement>
      <dates>
        <date>22/11/2016 17:44:33</date>
      </dates>
    </piece>
    <piece id="23997">
      <classement>
        <version date="22/11/2016 16:45:22" value="0012.1" />
      </classement>
    </piece>
    <piece id="23999">
      <classement>
        <version date="22/11/2016 10:28:38" value="0010.1" />
      </classement>
      <dates>
        <date>22/11/2016 10:28:04</date>
      </dates>
    </piece>
    <piece id="24103">
      <classement>
        <version date="22/11/2016 17:39:07" value="0005233.1" />
      </classement>
      <disabled />
    </piece>
    <piece id="24117">
      <classement>
        <version date="22/11/2016 10:38:51" value="0010.1" />
      </classement>
    </piece>
    <piece id="25101">
      <classement>
        <version date="22/11/2016 11:57:45" value="0044.5" />
      </classement>
    </piece>
    <piece id="25957">
      <classement>
        <version date="22/11/2016 18:16:57" value="0014.0" />
      </classement>
    </piece>
    <piece id="27115">
      <classement>
        <version date="22/11/2016 10:27:06" value="0010.2" />
      </classement>
    </piece>
    <piece id="27148">
      <classement>
        <version date="22/11/2016 16:41:47" value="0010.3" />
      </classement>
      <duration>354277</duration>
    </piece>
    <piece id="27260">
      <classement>
        <version date="22/11/2016 19:10:05" value="0043.4" />
      </classement>
      <duration>309398</duration>
    </piece>
    <piece id="27487">
      <classement>
        <version date="22/11/2016 18:07:04" value="0012.1" />
      </classement>
      <duration>295057</duration>
    </piece>
    <piece id="27567">
      <classement>
        <version date="22/11/2016 10:24:27" value="0005.4" />
      </classement>
    </piece>
    <piece id="28338">
      <classement>
        <version date="22/11/2016 10:54:25" value="00055.2" />
      </classement>
    </piece>
    <piece id="28344">
      <classement>
        <version date="22/11/2016 11:47:22" value="00101.4" />
      </classement>
    </piece>
    <piece id="28559">
      <classement>
        <version date="22/11/2016 11:50:01" value="0005344.0" />
      </classement>
      <disabled />
    </piece>
    <piece id="28560">
      <classement>
        <version date="22/11/2016 14:39:56" value="0015.2" />
      </classement>
    </piece>
    <piece id="28577">
      <classement>
        <version date="22/11/2016 15:15:58" value="0005325.0" />
      </classement>
      <disabled />
    </piece>
    <piece id="28578">
      <classement>
        <version date="22/11/2016 14:23:58" value="00054.2" />
      </classement>
    </piece>
    <piece id="28656">
      <classement>
        <version date="22/11/2016 16:57:00" value="0013.1" />
      </classement>
    </piece>
    <piece id="29030">
      <classement>
        <version date="22/11/2016 17:49:25" value="0010.3" />
      </classement>
    </piece>
    <piece id="29438">
      <classement>
        <version date="22/11/2016 13:59:25" value="0010.2" />
      </classement>
    </piece>
    <piece id="29558">
      <classement>
        <version date="22/11/2016 10:30:56" value="00515.3" />
      </classement>
    </piece>
    <piece id="30345">
      <classement>
        <version date="22/11/2016 13:33:08" value="0005301.1" />
      </classement>
      <disabled />
    </piece>
    <piece id="30412">
      <classement>
        <version date="22/11/2016 17:39:57" value="0010.4" />
      </classement>
    </piece>
    <piece id="30641">
      <classement>
        <version date="22/11/2016 16:53:50" value="0011.2" />
      </classement>
    </piece>
    <piece id="30657">
      <classement>
        <version date="22/11/2016 14:38:39" value="0015.4" />
      </classement>
    </piece>
    <piece id="31525">
      <classement>
        <version date="22/11/2016 18:49:29" value="0025.4" />
      </classement>
    </piece>
    <piece id="31884">
      <classement>
        <version date="22/11/2016 17:12:39" value="0005.3" />
      </classement>
    </piece>
    <piece id="32245">
      <classement>
        <version date="22/11/2016 15:59:36" value="0005450.0" />
      </classement>
      <dates>
        <date>22/11/2016 15:31:58</date>
      </dates>
      <disabled />
    </piece>
    <piece id="32246">
      <classement>
        <version date="22/11/2016 14:33:42" value="00053.1" />
      </classement>
    </piece>
    <piece id="32284">
      <classement>
        <version date="22/11/2016 14:29:34" value="0005421.0" />
      </classement>
      <disabled />
    </piece>
    <piece id="32360">
      <classement>
        <version date="22/11/2016 13:42:36" value="0021.2" />
      </classement>
    </piece>
    <piece id="32389">
      <classement>
        <version date="22/11/2016 11:48:10" value="0010.2" />
      </classement>
    </piece>
    <piece id="33374">
      <classement>
        <version date="22/11/2016 17:00:19" value="0005320.3" />
      </classement>
      <disabled />
    </piece>
    <piece id="33375">
      <classement>
        <version date="22/11/2016 11:16:54" value="0005334.0" />
      </classement>
      <disabled />
    </piece>
    <piece id="33491">
      <classement>
        <version date="22/11/2016 18:03:58" value="0010.3" />
      </classement>
    </piece>
    <piece id="33513">
      <classement>
        <version date="22/11/2016 11:54:51" value="0005.5" />
      </classement>
    </piece>
    <piece id="33584">
      <classement>
        <version date="22/11/2016 10:55:10" value="0005.5" />
      </classement>
    </piece>
    <piece id="33726">
      <classement>
        <version date="22/11/2016 19:01:28" value="0005433.0" />
      </classement>
      <disabled />
    </piece>
  </pieces>
</db>
