<?xml version="1.0" encoding="utf-8"?>
<db version="3" seq_piece="38153">
  <pieces>
    <piece id="5866">
      <classement>
        <version date="15/05/2017 13:54:24" value="0015141.3" />
      </classement>
      <disabled />
    </piece>
    <piece id="9074">
      <classement>
        <version date="15/05/2017 14:04:11" value="0020215.2" />
      </classement>
      <dates>
        <date>15/05/2017 14:01:58</date>
      </dates>
    </piece>
    <piece id="10267">
      <classement>
        <version date="15/05/2017 13:18:22" value="0015155.1" />
      </classement>
      <dates>
        <date>15/05/2017 13:18:46</date>
      </dates>
    </piece>
    <piece id="10276">
      <dates>
        <date>15/05/2017 13:17:44</date>
      </dates>
    </piece>
    <piece id="10800">
      <classement>
        <version date="15/05/2017 10:17:45" value="0015342.3" />
      </classement>
      <disabled />
    </piece>
    <piece id="11477">
      <classement>
        <version date="15/05/2017 13:25:23" value="0020510.4" />
      </classement>
    </piece>
    <piece id="13078">
      <classement>
        <version date="15/05/2017 10:50:25" value="0015154.1" />
      </classement>
    </piece>
    <piece id="13791">
      <classement>
        <version date="15/05/2017 14:27:16" value="003305.3" />
      </classement>
      <duration>432954</duration>
    </piece>
    <piece id="14374">
      <classement>
        <version date="15/05/2017 13:47:46" value="0014551.1" />
      </classement>
      <disabled />
    </piece>
    <piece id="15042">
      <classement>
        <version date="15/05/2017 13:36:41" value="0015134.2" />
      </classement>
    </piece>
    <piece id="17297">
      <classement>
        <version date="15/05/2017 13:51:31" value="0015145.2" />
      </classement>
    </piece>
    <piece id="17344">
      <classement>
        <version date="15/05/2017 17:21:35" value="00154104.1" />
      </classement>
      <dates>
        <date>15/05/2017 17:20:29</date>
      </dates>
    </piece>
    <piece id="18775">
      <classement>
        <version date="15/05/2017 18:02:37" value="0015403.3" />
      </classement>
      <disabled />
    </piece>
    <piece id="19371">
      <classement>
        <version date="15/05/2017 13:38:13" value="0014530.5" />
      </classement>
    </piece>
    <piece id="19538">
      <classement>
        <version date="15/05/2017 13:21:23" value="00152122.1" />
      </classement>
      <dates>
        <date>15/05/2017 13:22:00</date>
      </dates>
    </piece>
    <piece id="20102">
      <classement>
        <version date="15/05/2017 17:59:36" value="00154232.3" />
      </classement>
      <dates>
        <date>15/05/2017 17:57:28</date>
      </dates>
    </piece>
    <piece id="20448">
      <classement>
        <version date="15/05/2017 14:24:35" value="0015442.4" />
      </classement>
      <duration>264533</duration>
    </piece>
    <piece id="20833">
      <classement>
        <version date="15/05/2017 10:34:39" value="0015431.3" />
      </classement>
      <disabled />
    </piece>
    <piece id="23397">
      <classement>
        <version date="15/05/2017 13:41:58" value="0015235.5" />
      </classement>
    </piece>
    <piece id="30163">
      <classement>
        <version date="15/05/2017 18:03:52" value="00154301.1" />
      </classement>
    </piece>
    <piece id="30650">
      <classement>
        <version date="15/05/2017 17:53:30" value="0020414.3" />
      </classement>
      <dates>
        <date>15/05/2017 17:51:30</date>
      </dates>
    </piece>
    <piece id="32968">
      <classement>
        <version date="15/05/2017 13:45:28" value="0015255.3" />
      </classement>
      <disabled />
    </piece>
    <piece id="34460">
      <classement>
        <version date="15/05/2017 13:39:54" value="0014354.2" />
      </classement>
    </piece>
    <piece id="35735">
      <classement>
        <version date="15/05/2017 13:29:20" value="305.3" />
      </classement>
    </piece>
    <piece id="37468">
      <classement>
        <version date="15/05/2017 10:45:14" value="0013004.1" />
      </classement>
      <disabled />
    </piece>
    <piece id="37486">
      <classement>
        <version date="15/05/2017 10:25:03" value="0015422.3" />
      </classement>
      <disabled />
    </piece>
    <piece id="37630">
      <classement>
        <version date="15/05/2017 10:26:36" value="0015153.1" />
      </classement>
    </piece>
    <piece id="37736">
      <classement>
        <version date="15/05/2017 10:46:48" value="0021520.3" />
      </classement>
    </piece>
    <piece id="37919">
      <classement>
        <version date="15/05/2017 10:35:47" value="0015014.5" />
      </classement>
    </piece>
    <piece id="37939">
      <classement>
        <version date="15/05/2017 13:31:57" value="0014532.5" />
      </classement>
    </piece>
    <piece id="37980">
      <classement>
        <version date="15/05/2017 10:14:10" value="0014112.2" />
      </classement>
    </piece>
    <piece id="38019">
      <classement>
        <version date="15/05/2017 10:23:16" value="0015412.3" />
      </classement>
      <disabled />
    </piece>
    <piece id="38038">
      <classement>
        <version date="15/05/2017 10:20:34" value="004333.3" />
      </classement>
    </piece>
    <piece id="38062">
      <classement>
        <version date="15/05/2017 10:19:13" value="003051.5" />
      </classement>
    </piece>
    <piece id="38063">
      <classement>
        <version date="15/05/2017 13:32:39" value="00150141.1" />
      </classement>
    </piece>
    <piece id="38077">
      <classement>
        <version date="15/05/2017 10:08:26" value="003234.1" />
      </classement>
    </piece>
    <piece id="38078">
      <classement>
        <version date="15/05/2017 10:32:12" value="00550.3" />
      </classement>
    </piece>
    <piece id="38088">
      <classement>
        <version date="15/05/2017 10:27:49" value="004203.3" />
      </classement>
    </piece>
    <piece id="38091">
      <classement>
        <version date="15/05/2017 10:43:39" value="0012504.1" />
      </classement>
      <disabled />
    </piece>
    <piece id="38092">
      <classement>
        <version date="15/05/2017 13:58:22" value="00145232.3" />
      </classement>
      <dates>
        <date>15/05/2017 13:57:33</date>
      </dates>
    </piece>
    <piece id="38104">
      <classement>
        <version date="15/05/2017 10:12:12" value="214.4" />
      </classement>
    </piece>
    <piece id="38105">
      <classement>
        <version date="15/05/2017 10:30:02" value="003113.1" />
      </classement>
    </piece>
    <piece id="38106">
      <classement>
        <version date="15/05/2017 13:50:05" value="0014212.1" />
      </classement>
    </piece>
    <piece id="38123">
      <classement>
        <version date="15/05/2017 10:06:21" value="002422.2" />
      </classement>
    </piece>
    <piece id="38124">
      <classement>
        <version date="15/05/2017 10:22:12" value="0021410.3" />
      </classement>
    </piece>
    <piece id="38125">
      <classement>
        <version date="15/05/2017 13:34:43" value="00154201.1" />
      </classement>
      <dates>
        <date>15/05/2017 13:33:56</date>
      </dates>
    </piece>
    <piece id="38131">
      <disabled />
    </piece>
    <piece id="38139">
      <classement>
        <version date="15/05/2017 10:10:10" value="351.1" />
      </classement>
    </piece>
  </pieces>
</db>
