<?xml version="1.0" encoding="utf-8"?>
<db version="3" seq_piece="38373">
  <pieces>
    <piece id="1301">
      <files>
        <file>bib20\1972\13 Without you.mp3</file>
      </files>
    </piece>
    <piece id="1929">
      <classement>
        <version date="09/06/2017 11:12:54" value="0021214.3" />
      </classement>
    </piece>
    <piece id="6613">
      <classement>
        <version date="09/06/2017 13:44:57" value="0015232.1" />
      </classement>
      <disabled />
    </piece>
    <piece id="7010">
      <classement>
        <version date="09/06/2017 13:32:35" value="0020103.3" />
      </classement>
      <disabled />
    </piece>
    <piece id="7127">
      <classement>
        <version date="09/06/2017 14:09:58" value="0020044.3" />
      </classement>
      <disabled />
    </piece>
    <piece id="8905">
      <classement>
        <version date="09/06/2017 14:00:31" value="00154102.3" />
      </classement>
    </piece>
    <piece id="8920">
      <classement>
        <version date="09/06/2017 11:29:11" value="0012544.1" />
      </classement>
      <disabled />
    </piece>
    <piece id="9096">
      <classement>
        <version date="09/06/2017 13:38:11" value="01250.1" />
      </classement>
      <dates>
        <date>09/06/2017 13:37:48</date>
      </dates>
    </piece>
    <piece id="10808">
      <classement>
        <version date="09/06/2017 15:35:12" value="0021111.4" />
      </classement>
    </piece>
    <piece id="10968">
      <classement>
        <version date="09/06/2017 11:34:54" value="00451.3" />
      </classement>
    </piece>
    <piece id="11802">
      <classement>
        <version date="09/06/2017 15:18:00" />
      </classement>
      <dates>
        <date>09/06/2017 15:17:49</date>
      </dates>
      <disabled />
    </piece>
    <piece id="12461">
      <classement>
        <version date="09/06/2017 11:33:00" value="0020530.3" />
      </classement>
      <duration>158533</duration>
    </piece>
    <piece id="13703">
      <classement>
        <version date="24/11/2014 12:12:53" value="02521.0" />
        <version date="20/09/2014 13:58:01" value="02223.1" />
        <version date="15/04/2014 10:22:31" value="125.0" />
        <version date="18/01/2014 16:41:04" value="124.0" />
        <version date="27/10/2013 10:21:30" value="11.0" />
        <version date="12/07/2013 21:47:09" value="1.0" />
      </classement>
      <files>
        <file>bib20\1972\13 Without you.mp3</file>
        <file>Compilations\Le Meilleur De La Variété Internationale\10 Harry Nilsson _ Without You.mp3</file>
      </files>
      <dates>
        <date>24/11/2014 12:00:50</date>
        <date>26/05/2014 16:44:32</date>
        <date>23/01/2014 17:04:58</date>
        <date>18/01/2014 12:41:48</date>
        <date>26/10/2013 14:38:18</date>
        <date>26/10/2013 13:01:06</date>
        <date>19/12/2012 22:02:31</date>
        <date>23/09/2012 23:04:39</date>
      </dates>
    </piece>
    <piece id="32189" parent="13703" />
    <piece id="14060">
      <classement>
        <version date="09/06/2017 14:03:04" value="0014404.3" />
      </classement>
      <disabled />
    </piece>
    <piece id="14079">
      <classement>
        <version date="09/06/2017 11:41:13" value="003231.3" />
      </classement>
    </piece>
    <piece id="14803">
      <classement>
        <version date="09/06/2017 11:27:25" value="0012314.1" />
      </classement>
      <disabled />
    </piece>
    <piece id="15356">
      <classement>
        <version date="09/06/2017 15:37:56" value="0014202.1" />
      </classement>
      <dates>
        <date>09/06/2017 15:37:19</date>
      </dates>
      <disabled />
    </piece>
    <piece id="15511">
      <classement>
        <version date="09/06/2017 10:36:50" value="0020130.3" />
      </classement>
      <disabled />
    </piece>
    <piece id="15598">
      <classement>
        <version date="09/06/2017 11:15:49" value="0022023.3" />
      </classement>
    </piece>
    <piece id="15780">
      <classement>
        <version date="09/06/2017 13:09:54" value="0015543.1" />
      </classement>
      <disabled />
    </piece>
    <piece id="15880">
      <classement>
        <version date="09/06/2017 13:39:27" value="0015102.1" />
      </classement>
      <disabled />
    </piece>
    <piece id="15891">
      <classement>
        <version date="09/06/2017 11:06:41" value="0021324.3" />
      </classement>
      <dates>
        <date>09/06/2017 11:06:02</date>
      </dates>
    </piece>
    <piece id="17107">
      <classement>
        <version date="09/06/2017 13:47:42" value="0010004.3" />
      </classement>
      <disabled />
    </piece>
    <piece id="17947">
      <classement>
        <version date="09/06/2017 13:41:57" value="0014254.1" />
      </classement>
      <disabled />
    </piece>
    <piece id="19716">
      <classement>
        <version date="09/06/2017 13:17:10" value="0015304.1" />
      </classement>
      <dates>
        <date>09/06/2017 13:16:09</date>
      </dates>
      <disabled />
    </piece>
    <piece id="20293">
      <classement>
        <version date="09/06/2017 11:30:53" value="0020002.3" />
      </classement>
      <disabled />
    </piece>
    <piece id="20594">
      <classement>
        <version date="09/06/2017 11:18:02" value="0015002.1" />
      </classement>
      <disabled />
    </piece>
    <piece id="21372">
      <classement>
        <version date="09/06/2017 11:11:55" value="0020200.3" />
      </classement>
      <disabled />
    </piece>
    <piece id="21822">
      <classement>
        <version date="09/06/2017 15:14:07" value="0015514.1" />
      </classement>
      <disabled />
    </piece>
    <piece id="22688">
      <classement>
        <version date="09/06/2017 10:29:05" value="0020122.5" />
      </classement>
      <dates>
        <date>09/06/2017 10:29:35</date>
      </dates>
    </piece>
    <piece id="23011">
      <classement>
        <version date="09/06/2017 11:42:32" value="0020032.0" />
      </classement>
      <disabled />
    </piece>
    <piece id="23791">
      <classement>
        <version date="09/06/2017 10:33:57" value="0021010.4" />
      </classement>
    </piece>
    <piece id="24022">
      <classement>
        <version date="09/06/2017 11:40:17" value="00202100.1" />
      </classement>
    </piece>
    <piece id="24240">
      <classement>
        <version date="09/06/2017 13:09:02" value="0020230.3" />
      </classement>
      <dates>
        <date>09/06/2017 13:08:42</date>
      </dates>
      <disabled />
    </piece>
    <piece id="25041">
      <classement>
        <version date="09/06/2017 13:35:14" value="00154245.3" />
      </classement>
    </piece>
    <piece id="26242">
      <classement>
        <version date="09/06/2017 13:24:34" value="00145201.1" />
      </classement>
      <dates>
        <date>09/06/2017 13:24:15</date>
      </dates>
    </piece>
    <piece id="26989">
      <classement>
        <version date="09/06/2017 13:28:30" value="00154022.1" />
      </classement>
    </piece>
    <piece id="27100">
      <classement>
        <version date="09/06/2017 11:35:59" value="0014554.1" />
      </classement>
      <disabled />
    </piece>
    <piece id="27568">
      <classement>
        <version date="09/06/2017 11:31:41" value="0015521.1" />
      </classement>
      <disabled />
    </piece>
    <piece id="27383" parent="27568" />
    <piece id="29043">
      <classement>
        <version date="09/06/2017 10:39:00" value="002041.2" />
      </classement>
      <disabled />
    </piece>
    <piece id="30110">
      <classement>
        <version date="09/06/2017 14:11:49" value="0022120.3" />
      </classement>
    </piece>
    <piece id="30875">
      <classement>
        <version date="09/06/2017 15:51:46" value="0022221.1" />
      </classement>
    </piece>
    <piece id="31833">
      <classement>
        <version date="09/06/2017 11:36:49" value="0021110.2" />
      </classement>
    </piece>
    <piece id="31964">
      <classement>
        <version date="09/06/2017 15:56:48" value="205.4" />
      </classement>
    </piece>
    <piece id="32537">
      <classement>
        <version date="09/06/2017 14:08:59" value="0020012.3" />
      </classement>
      <disabled />
    </piece>
    <piece id="33477">
      <classement>
        <version date="09/06/2017 11:25:26" value="0015204.1" />
      </classement>
      <disabled />
    </piece>
    <piece id="34026">
      <classement>
        <version date="09/06/2017 15:20:12" value="0010354.1" />
      </classement>
      <disabled />
    </piece>
    <piece id="35424">
      <classement>
        <version date="09/06/2017 10:44:52" value="0015504.1" />
      </classement>
      <dates>
        <date>09/06/2017 10:43:24</date>
      </dates>
      <disabled />
    </piece>
    <piece id="35743">
      <classement>
        <version date="09/06/2017 11:19:56" value="0021233.3" />
      </classement>
    </piece>
    <piece id="35890">
      <classement>
        <version date="09/06/2017 11:00:15" value="0020140.3" />
      </classement>
      <dates />
    </piece>
    <piece id="36327">
      <classement>
        <version date="09/06/2017 14:06:29" value="0020224.2" />
      </classement>
    </piece>
    <piece id="36837">
      <classement>
        <version date="09/06/2017 13:40:23" value="0020101.4" />
      </classement>
    </piece>
    <piece id="36937">
      <classement>
        <version date="09/06/2017 13:12:08" value="0020041.3" />
      </classement>
      <disabled />
    </piece>
    <piece id="37039">
      <classement>
        <version date="09/06/2017 11:08:32" value="0020101.3" />
      </classement>
    </piece>
    <piece id="37234">
      <classement>
        <version date="09/06/2017 15:15:27" value="002034.2" />
      </classement>
      <disabled />
    </piece>
    <piece id="37581">
      <classement>
        <version date="09/06/2017 13:56:56" value="0015554.3" />
      </classement>
      <dates>
        <date>09/06/2017 13:51:14</date>
      </dates>
      <disabled />
    </piece>
    <piece id="37829">
      <classement>
        <version date="09/06/2017 13:58:47" value="003254.1" />
      </classement>
      <dates>
        <date>09/06/2017 13:55:44</date>
      </dates>
    </piece>
    <piece id="37890">
      <classement>
        <version date="09/06/2017 11:01:51" value="00201211.1" />
      </classement>
    </piece>
    <piece id="38190">
      <classement>
        <version date="09/06/2017 15:29:23" value="00145214.1" />
      </classement>
    </piece>
    <piece id="38195">
      <classement>
        <version date="09/06/2017 13:19:59" value="00201113.1" />
      </classement>
    </piece>
    <piece id="38198">
      <classement>
        <version date="09/06/2017 11:37:48" value="00202133.3" />
      </classement>
    </piece>
    <piece id="38199">
      <classement>
        <version date="09/06/2017 15:55:21" value="0020030.2" />
      </classement>
    </piece>
    <piece id="38213">
      <classement>
        <version date="09/06/2017 15:25:39" value="0020131.2" />
      </classement>
    </piece>
    <piece id="38247">
      <classement>
        <version date="09/06/2017 11:10:13" value="002050.2" />
      </classement>
    </piece>
    <piece id="38248">
      <classement>
        <version date="09/06/2017 15:44:26" value="0013254.1" />
      </classement>
      <dates>
        <date>09/06/2017 15:43:34</date>
      </dates>
      <disabled />
    </piece>
    <piece id="38271">
      <classement>
        <version date="09/06/2017 15:27:31" value="0020524.1" />
      </classement>
    </piece>
    <piece id="38284">
      <classement>
        <version date="09/06/2017 15:54:13" value="0015452.4" />
      </classement>
    </piece>
    <piece id="38308">
      <classement>
        <version date="09/06/2017 15:24:10" value="0020143.3" />
      </classement>
    </piece>
    <piece id="38318">
      <classement>
        <version date="09/06/2017 13:26:46" value="0013354.1" />
      </classement>
      <disabled />
    </piece>
    <piece id="38339">
      <classement>
        <version date="09/06/2017 15:31:10" value="002130.1" />
      </classement>
    </piece>
    <piece id="38345">
      <classement>
        <version date="09/06/2017 15:53:11" value="0015442.5" />
      </classement>
    </piece>
    <piece id="38354">
      <classement>
        <version date="09/06/2017 15:11:04" value="0013502.1" />
      </classement>
      <disabled />
    </piece>
    <piece id="38363">
      <classement>
        <version date="09/06/2017 13:21:41" value="0012414.1" />
      </classement>
    </piece>
    <piece id="38366">
      <classement>
        <version date="09/06/2017 15:33:37" value="0014302.1" />
      </classement>
      <disabled />
    </piece>
  </pieces>
</db>
