<?xml version="1.0" encoding="utf-8"?>
<db version="3" seq_piece="25347">
  <pieces>
    <piece id="41">
      <classement>
        <version>
          <date>11/01/2016 11:10:59</date>
          <class>3344</class>
          <rating>0</rating>
        </version>
      </classement>
      <dates>
        <date>11/01/2016 11:12:06</date>
      </dates>
      <disabled />
    </piece>
    <piece id="673">
      <classement>
        <version>
          <date>11/01/2016 15:45:17</date> 
          <class>2011</class>
          <rating>0</rating>
        </version>
      </classement>
      <dates>
        <date>11/01/2016 15:47:01</date>
      </dates>
      <disabled />
      <duration>181670</duration>
    </piece>
    <piece id="1016">
      <classement>
        <version>
          <date>11/01/2016 17:06:59</date>
          <class>3041</class>
          <rating>0</rating>
        </version>
      </classement>
      <disabled />
    </piece>
    <piece id="13510" parent="1016">
      <disabled />
    </piece>
    <piece id="1055">
      <classement>
        <version>
          <date>11/01/2016 16:40:59</date>
          <class>3234</class>
          <rating>0</rating>
        </version>
      </classement>
      <dates>
        <date>11/01/2016 16:43:18</date>
      </dates>
      <disabled />
      <duration>227000</duration>
    </piece>
    <piece id="1143">
      <duration>204278</duration>
    </piece>
    <piece id="1420">
      <classement>
        <version>
          <date>11/01/2016 17:26:12</date>
          <class>2553</class>
          <rating>0</rating>
        </version>
      </classement>
      <dates>
        <date>11/01/2016 17:26:56</date>
      </dates>
      <disabled />
    </piece>
    <piece id="2810">
      <classement>
        <version>
          <date>11/01/2016 11:16:44</date>
          <class>1544</class>
          <rating>0</rating>
        </version>
      </classement>
      <disabled />
    </piece>
    <piece id="2820">
      <classement>
        <version>
          <date>11/01/2016 16:24:09</date>
          <class>2134</class>
          <rating>0</rating>
        </version>
      </classement>
      <disabled />
      <duration>203788</duration>
    </piece>
    <piece id="3053">
      <classement>
        <version>
          <date>11/01/2016 15:47:58</date>
          <class>1412</class>
          <rating>0</rating>
        </version>
      </classement>
      <disabled />
      <duration>152661</duration>
    </piece>
    <piece id="3756">
      <classement>
        <version>
          <date>11/01/2016 16:21:07</date>
          <class>3511</class>
          <rating>0</rating>
        </version>
      </classement>
      <dates>
        <date>11/01/2016 16:22:14</date>
      </dates>
      <disabled />
    </piece>
    <piece id="4549">
      <classement>
        <version>
          <date>11/01/2016 16:36:39</date>
          <class>3131</class>
          <rating>0</rating>
        </version>
      </classement>
      <dates>
        <date>11/01/2016 16:39:31</date>
      </dates>
      <disabled />
      <duration>231112</duration>
    </piece>
    <piece id="5134">
      <classement>
        <version>
          <date>11/01/2016 16:18:26</date>
          <class>001510</class>
          <rating>0</rating>
        </version>
      </classement>
      <dates>
        <date>11/01/2016 16:18:40</date>
      </dates>
      <disabled />
    </piece>
    <piece id="5347">
      <classement>
        <version>
          <date>11/01/2016 11:13:38</date>
          <class>3011</class>
          <rating>0</rating>
        </version>
      </classement>
      <dates>
        <date>11/01/2016 11:15:05</date>
      </dates>
      <disabled />
    </piece>
    <piece id="5922">
      <classement>
        <version>
          <date>11/01/2016 15:23:29</date>
          <class>3441</class>
          <rating>0</rating>
        </version>
      </classement>
      <dates>
        <date>11/01/2016 15:25:56</date>
      </dates>
      <disabled />
    </piece>
    <piece id="6276">
      <classement>
        <version>
          <date>11/01/2016 14:20:06</date>
          <class>2221</class>
          <rating>0</rating>
        </version>
      </classement>
      <disabled />
    </piece>
    <piece id="6459">
      <classement>
        <version>
          <date>11/01/2016 14:29:27</date>
          <class>03003</class>
          <rating>0</rating>
        </version>
      </classement>
      <dates>
        <date>11/01/2016 14:28:54</date>
      </dates>
      <disabled />
      <duration>208223</duration>
    </piece>
    <piece id="6967">
      <classement>
        <version>
          <date>11/01/2016 15:43:46</date>
          <class>01203</class>
          <rating>0</rating>
        </version>
      </classement>
      <dates>
        <date>11/01/2016 15:43:59</date>
      </dates>
      <disabled />
    </piece>
    <piece id="7345">
      <classement>
        <version>
          <date>11/01/2016 17:08:52</date>
          <class>3453</class>
          <rating>0</rating>
        </version>
      </classement>
      <dates>
        <date>11/01/2016 17:10:49</date>
      </dates>
      <disabled />
    </piece>
    <piece id="7425">
      <classement>
        <version>
          <date>11/01/2016 11:26:16</date>
          <class>001430</class>
          <rating>0</rating>
        </version>
      </classement>
      <disabled />
      <duration>203234</duration>
    </piece>
    <piece id="7443">
      <classement>
        <version>
          <date>11/01/2016 16:45:50</date>
          <class>1103</class>
          <rating>20</rating>
        </version>
      </classement>
      <dates>
        <date>11/01/2016 16:46:40</date>
      </dates>
      <disabled />
      <duration>201954</duration>
    </piece>
    <piece id="7573">
      <classement>
        <version>
          <date>11/01/2016 17:57:50</date>
          <class>1335</class>
          <rating>0</rating>
        </version>
      </classement>
      <dates>
        <date>11/01/2016 17:57:50</date>
      </dates>
      <disabled />
    </piece>
    <piece id="7574">
      <duration>300597</duration>
    </piece>
    <piece id="7669">
      <classement>
        <version>
          <date>11/01/2016 14:42:42</date>
          <class>04003</class>
          <rating>0</rating>
        </version>
      </classement>
      <disabled />
    </piece>
    <piece id="7711">
      <classement>
        <version>
          <date>11/01/2016 14:31:45</date>
          <class>1325</class>
          <rating>0</rating>
        </version>
      </classement>
      <dates>
        <date>11/01/2016 14:35:06</date>
      </dates>
      <disabled />
    </piece>
    <piece id="12629" parent="7711">
      <disabled />
      <duration>335781</duration>
    </piece>
    <piece id="7878">
      <classement>
        <version>
          <date>11/01/2016 15:39:14</date>
          <class>2252</class>
          <rating>0</rating>
        </version>
      </classement>
      <dates>
        <date>11/01/2016 15:39:22</date>
      </dates>
      <disabled />
    </piece>
    <piece id="8151">
      <classement>
        <version>
          <date>11/01/2016 14:40:41</date>
          <class>002410</class>
          <rating>0</rating>
        </version>
      </classement>
      <disabled />
      <duration>214624</duration>
    </piece>
    <piece id="9041">
      <classement>
        <version>
          <date>11/01/2016 14:25:15</date>
          <class>3312</class>
          <rating>0</rating>
        </version>
      </classement>
      <dates>
        <date>11/01/2016 14:25:25</date>
      </dates>
      <disabled />
      <duration>217455</duration>
    </piece>
    <piece id="9462">
      <classement>
        <version>
          <date>11/01/2016 11:29:54</date>
        </version>
      </classement>
      <dates>
        <date>11/01/2016 11:30:05</date>
      </dates>
      <disabled />
    </piece>
    <piece id="9466">
      <classement>
        <version>
          <date>11/01/2016 16:29:41</date>
          <class>004430</class>
          <rating>0</rating>
        </version>
      </classement>
      <dates>
        <date>11/01/2016 16:29:09</date>
      </dates>
      <disabled />
      <duration>194248</duration>
    </piece>
    <piece id="9467">
      <duration>215902</duration>
    </piece>
    <piece id="10890">
      <classement>
        <version>
          <date>11/01/2016 11:19:36</date>
          <class>1205</class>
          <rating>0</rating>
        </version>
      </classement>
      <dates>
        <date>11/01/2016 11:22:13</date>
      </dates>
      <disabled />
    </piece>
    <piece id="10990">
      <classement>
        <version>
          <date>11/01/2016 14:40:03</date>
          <class>03301</class>
          <rating>0</rating>
        </version>
      </classement>
      <disabled />
    </piece>
    <piece id="11690">
      <classement>
        <version>
          <date>11/01/2016 16:32:29</date>
          <class>1230</class>
          <rating>20</rating>
        </version>
      </classement>
      <dates>
        <date>11/01/2016 16:33:23</date>
      </dates>
      <disabled />
    </piece>
    <piece id="12200">
      <classement>
        <version>
          <date>11/01/2016 15:15:19</date>
          <class>04103</class>
          <rating>0</rating>
        </version>
      </classement>
      <disabled />
    </piece>
    <piece id="12326">
      <classement>
        <version>
          <date>11/01/2016 15:22:33</date>
          <class>2102</class>
          <rating>0</rating>
        </version>
      </classement>
      <dates>
        <date>11/01/2016 15:22:50</date>
      </dates>
      <disabled />
    </piece>
    <piece id="12814">
      <classement>
        <version>
          <date>11/01/2016 17:53:27</date>
          <class>1140</class>
          <rating>20</rating>
        </version>
      </classement>
      <disabled />
    </piece>
    <piece id="12944">
      <classement>
        <version>
          <date>11/01/2016 15:28:16</date>
          <class>1522</class>
          <rating>0</rating>
        </version>
      </classement>
      <dates>
        <date>11/01/2016 15:30:00</date>
      </dates>
      <disabled />
    </piece>
    <piece id="13380">
      <classement>
        <version>
          <date>11/01/2016 16:34:21</date>
          <class>2453</class>
          <rating>0</rating>
        </version>
      </classement>
      <disabled />
    </piece>
    <piece id="13464">
      <classement>
        <version>
          <date>11/01/2016 16:52:23</date>
          <class>1210</class>
          <rating>60</rating>
        </version>
      </classement>
      <dates>
        <date>11/01/2016 16:52:46</date>
      </dates>
      <disabled />
    </piece>
    <piece id="13796">
      <classement>
        <version>
          <date>11/01/2016 15:12:49</date>
          <class>1003</class>
          <rating>60</rating>
        </version>
      </classement>
      <dates>
        <date>11/01/2016 15:13:34</date>
      </dates>
      <disabled />
    </piece>
    <piece id="13841">
      <classement>
        <version>
          <date>11/01/2016 15:42:46</date>
          <class>03403</class>
          <rating>0</rating>
        </version>
      </classement>
      <dates>
        <date>11/01/2016 15:42:58</date>
      </dates>
      <disabled />
    </piece>
    <piece id="13977">
      <classement>
        <version>
          <date>11/01/2016 18:16:22</date>
          <class>01233</class>
          <rating>0</rating>
        </version>
      </classement>
      <dates>
        <date>11/01/2016 18:15:46</date>
      </dates>
      <disabled />
    </piece>
    <piece id="14547">
      <classement>
        <version>
          <date>11/01/2016 16:49:39</date>
          <class>2044</class>
          <rating>0</rating>
        </version>
      </classement>
      <dates>
        <date>11/01/2016 16:49:42</date>
      </dates>
      <disabled />
    </piece>
    <piece id="14985">
      <classement>
        <version>
          <date>11/01/2016 15:48:58</date>
          <class>2343</class>
          <rating>0</rating>
        </version>
      </classement>
      <dates>
        <date>11/01/2016 15:50:55</date>
      </dates>
      <disabled />
    </piece>
    <piece id="15780">
      <classement>
        <version>
          <date>11/01/2016 11:08:59</date>
          <class>04303</class>
          <rating>0</rating>
        </version>
      </classement>
      <dates>
        <date>11/01/2016 11:09:23</date>
      </dates>
      <disabled />
    </piece>
    <piece id="15904">
      <classement>
        <version>
          <date>11/01/2016 18:09:56</date>
          <class>1033</class>
          <rating>60</rating>
        </version>
      </classement>
      <dates>
        <date>11/01/2016 18:10:53</date>
      </dates>
      <disabled />
    </piece>
    <piece id="16110">
      <classement>
        <version>
          <date>11/01/2016 15:36:48</date>
          <class>05201</class>
          <rating>0</rating>
        </version>
      </classement>
      <dates>
        <date>11/01/2016 15:37:49</date>
      </dates>
      <disabled />
    </piece>
    <piece id="16536">
      <classement>
        <version>
          <date>11/01/2016 14:37:20</date>
          <class>0005100</class>
          <rating>0</rating>
        </version>
      </classement>
      <dates>
        <date>11/01/2016 14:38:15</date>
      </dates>
      <disabled />
    </piece>
    <piece id="16547">
      <classement>
        <version>
          <date>11/01/2016 15:54:07</date>
          <class>003210</class>
          <rating>0</rating>
        </version>
      </classement>
      <dates>
        <date>11/01/2016 15:53:07</date>
      </dates>
      <disabled />
    </piece>
    <piece id="16833">
      <classement>
        <version>
          <date>11/01/2016 11:28:13</date>
          <class>02303</class>
          <rating>0</rating>
        </version>
      </classement>
      <dates>
        <date>11/01/2016 11:29:04</date>
      </dates>
      <disabled />
    </piece>
    <piece id="17132">
      <classement>
        <version>
          <date>11/01/2016 15:16:48</date>
          <class>02101</class>
          <rating>0</rating>
        </version>
      </classement>
      <disabled />
    </piece>
    <piece id="17142">
      <classement>
        <version>
          <date>11/01/2016 15:26:46</date>
          <class>00001010</class>
          <rating>0</rating>
        </version>
      </classement>
      <disabled />
    </piece>
    <piece id="17241">
      <classement>
        <version>
          <date>11/01/2016 14:59:35</date>
          <class>2034</class>
          <rating>0</rating>
        </version>
      </classement>
      <disabled />
    </piece>
    <piece id="17347">
      <classement>
        <version>
          <date>11/01/2016 17:11:57</date>
          <class>04403</class>
          <rating>0</rating>
        </version>
      </classement>
      <dates>
        <date>11/01/2016 17:13:25</date>
      </dates>
      <disabled />
    </piece>
    <piece id="17574">
      <classement>
        <version>
          <date>11/01/2016 16:14:31</date>
          <class>1130</class>
          <rating>60</rating>
        </version>
      </classement>
      <disabled />
    </piece>
    <piece id="17960">
      <classement>
        <version>
          <date>11/01/2016 15:18:46</date>
          <class>05101</class>
          <rating>0</rating>
        </version>
      </classement>
      <disabled />
    </piece>
    <piece id="18017">
      <classement>
        <version>
          <date>11/01/2016 15:02:41</date>
          <class>1434</class>
          <rating>0</rating>
        </version>
      </classement>
      <disabled />
    </piece>
    <piece id="18332">
      <classement>
        <version>
          <date>11/01/2016 17:54:56</date>
          <class>0001210</class>
          <rating>0</rating>
        </version>
      </classement>
      <disabled />
    </piece>
    <piece id="18439">
      <classement>
        <version>
          <date>11/01/2016 17:14:26</date>
          <class>1240</class>
          <rating>60</rating>
        </version>
      </classement>
      <dates>
        <date>11/01/2016 17:17:27</date>
      </dates>
      <disabled />
    </piece>
    <piece id="18676">
      <classement>
        <version>
          <date>11/01/2016 11:23:28</date>
          <class>01011</class>
          <rating>0</rating>
        </version>
      </classement>
      <disabled />
    </piece>
    <piece id="18805">
      <artist>
        <version>
          <date>11/01/2016 15:18:22</date>
          <value>1931</value>
        </version>
      </artist>
    </piece>
    <piece id="19027">
      <classement>
        <version>
          <date>11/01/2016 15:31:44</date>
          <class>05401</class>
          <rating>0</rating>
        </version>
      </classement>
      <dates>
        <date>11/01/2016 15:33:14</date>
      </dates>
      <disabled />
    </piece>
    <piece id="19052">
      <disabled />
    </piece>
    <piece id="19193">
      <classement>
        <version>
          <date>11/01/2016 16:58:39</date>
          <class>3225</class>
          <rating>0</rating>
        </version>
      </classement>
      <dates>
        <date>11/01/2016 17:01:26</date>
      </dates>
      <disabled />
    </piece>
    <piece id="20024">
      <classement>
        <version>
          <date>11/01/2016 16:35:33</date>
          <class>01301</class>
          <rating>0</rating>
        </version>
      </classement>
      <disabled />
    </piece>
    <piece id="20241">
      <classement>
        <version>
          <date>11/01/2016 16:15:16</date>
          <class>00001400</class>
          <rating>0</rating>
        </version>
      </classement>
      <dates>
        <date>11/01/2016 16:15:23</date>
      </dates>
      <disabled />
    </piece>
    <piece id="21731">
      <classement>
        <version>
          <date>11/01/2016 17:18:15</date>
        </version>
      </classement>
      <dates>
        <date>11/01/2016 17:18:01</date>
      </dates>
      <disabled />
    </piece>
    <piece id="21732">
      <classement>
        <version>
          <date>11/01/2016 17:18:59</date>
          <class>02403</class>
          <rating>0</rating>
        </version>
      </classement>
      <dates>
        <date>11/01/2016 17:22:29</date>
      </dates>
      <disabled />
    </piece>
    <piece id="22099">
      <classement>
        <version>
          <date>11/01/2016 18:12:36</date>
          <class>05501</class>
          <rating>0</rating>
        </version>
      </classement>
      <disabled />
    </piece>
    <piece id="22410">
      <classement>
        <version>
          <date>11/01/2016 16:55:14</date>
          <class>01133</class>
          <rating>0</rating>
        </version>
      </classement>
      <dates>
        <date>11/01/2016 16:56:26</date>
      </dates>
      <disabled />
    </piece>
    <piece id="22773">
      <classement>
        <version>
          <date>11/01/2016 14:55:48</date>
          <class>1050</class>
          <rating>60</rating>
        </version>
      </classement>
      <dates>
        <date>11/01/2016 14:58:25</date>
        <date>11/01/2016 14:48:44</date>
      </dates>
      <disabled />
    </piece>
    <piece id="23050">
      <classement>
        <version>
          <date>11/01/2016 17:04:08</date>
          <class>0001130</class>
          <rating>0</rating>
        </version>
      </classement>
      <dates>
        <date>11/01/2016 17:03:51</date>
      </dates>
      <disabled />
    </piece>
    <piece id="23310">
      <classement>
        <version>
          <date>11/01/2016 18:17:36</date>
          <class>02211</class>
          <rating>0</rating>
        </version>
      </classement>
      <disabled />
    </piece>
    <piece id="23969">
      <classement>
        <version>
          <date>11/01/2016 17:24:03</date>
          <class>03101</class>
          <rating>0</rating>
        </version>
      </classement>
      <disabled />
    </piece>
    <piece id="24006">
      <classement>
        <version>
          <date>11/01/2016 18:06:34</date>
          <class>005130</class>
          <rating>0</rating>
        </version>
      </classement>
      <dates>
        <date>11/01/2016 18:06:56</date>
      </dates>
      <disabled />
    </piece>
  </pieces>
</db>
