<?xml version="1.0" encoding="utf-8"?>
<db version="3" seq_piece="31438">
  <pieces>
    <piece id="260">
      <classement>
        <version>
          <date>09/02/2016 11:28:41</date>
          <class>001543</class>
          <rating>0</rating>
        </version>
      </classement>
      <dates>
        <date>09/02/2016 11:28:52</date>
      </dates>
      <disabled />
    </piece>
    <piece id="1695">
      <duration>180000</duration>
    </piece>
    <piece id="6412">
      <classement>
        <version>
          <date>09/02/2016 17:36:25</date>
          <class>001101</class>
          <rating>0</rating>
        </version>
      </classement>
      <disabled />
      <duration>218828</duration>
    </piece>
    <piece id="7219">
      <classement>
        <version>
          <date>09/02/2016 17:13:38</date>
          <class>00003143</class>
          <rating>0</rating>
        </version>
      </classement>
      <disabled />
    </piece>
    <piece id="9623">
      <classement>
        <version>
          <date>09/02/2016 14:45:08</date>
          <class>0003303</class>
          <rating>0</rating>
        </version>
      </classement>
      <dates>
        <date>09/02/2016 14:45:53</date>
      </dates>
      <disabled />
    </piece>
    <piece id="12746">
      <classement>
        <version>
          <date>09/02/2016 14:43:16</date>
          <class>001423</class>
          <rating>0</rating>
        </version>
      </classement>
      <dates>
        <date>09/02/2016 14:43:49</date>
      </dates>
      <disabled />
      <duration>154133</duration>
    </piece>
    <piece id="15286">
      <classement>
        <version>
          <date>09/02/2016 14:50:43</date>
          <class>0002413</class>
          <rating>0</rating>
        </version>
      </classement>
      <disabled />
    </piece>
    <piece id="16968">
      <classement>
        <version>
          <date>09/02/2016 11:21:47</date>
          <class>000003520</class>
          <rating>0</rating>
        </version>
      </classement>
      <disabled />
    </piece>
    <piece id="16969">
      <classement>
        <version>
          <date>09/02/2016 14:39:45</date>
          <class>00004233</class>
          <rating>0</rating>
        </version>
      </classement>
      <disabled />
    </piece>
    <piece id="17109">
      <classement>
        <version>
          <date>09/02/2016 19:08:00</date>
          <class>02504</class>
          <rating>0</rating>
        </version>
      </classement>
      <disabled />
    </piece>
    <piece id="18298">
      <classement>
        <version>
          <date>09/02/2016 11:16:51</date>
          <class>0003120</class>
          <rating>0</rating>
        </version>
      </classement>
      <disabled />
    </piece>
    <piece id="18337">
      <classement>
        <version>
          <date>09/02/2016 11:13:08</date>
          <class>00001404</class>
          <rating>0</rating>
        </version>
      </classement>
      <disabled />
    </piece>
    <piece id="18338">
      <classement>
        <version>
          <date>09/02/2016 17:14:48</date>
          <class>00001254</class>
          <rating>0</rating>
        </version>
      </classement>
      <disabled />
      <duration>258600</duration>
    </piece>
    <piece id="18339">
      <classement>
        <version>
          <date>09/02/2016 17:45:50</date>
          <class>00001232</class>
          <rating>0</rating>
        </version>
      </classement>
      <disabled />
      <duration>173627</duration>
    </piece>
    <piece id="18340">
      <classement>
        <version>
          <date>09/02/2016 18:53:00</date>
          <class>00004213</class>
          <rating>0</rating>
        </version>
      </classement>
      <disabled />
      <duration>216867</duration>
    </piece>
    <piece id="18356">
      <classement>
        <version>
          <date>09/02/2016 11:43:31</date>
          <class>0005340</class>
          <rating>0</rating>
        </version>
      </classement>
      <disabled />
    </piece>
    <piece id="18556">
      <classement>
        <version>
          <date>09/02/2016 18:16:11</date>
          <class>0002443</class>
          <rating>0</rating>
        </version>
      </classement>
      <dates>
        <date>09/02/2016 18:41:08</date>
      </dates>
      <disabled />
    </piece>
    <piece id="18654">
      <classement>
        <version>
          <date>09/02/2016 11:40:57</date>
          <class>00001102</class>
          <rating>0</rating>
        </version>
      </classement>
      <disabled />
    </piece>
    <piece id="18655">
      <classement>
        <version>
          <date>09/02/2016 17:12:27</date>
          <class>00005103</class>
          <rating>0</rating>
        </version>
      </classement>
      <dates>
        <date>09/02/2016 17:11:14</date>
        <date>09/02/2016 17:06:09</date>
      </dates>
      <disabled />
    </piece>
    <piece id="18746">
      <classement>
        <version>
          <date>09/02/2016 11:36:13</date>
        </version>
      </classement>
      <dates>
        <date>09/02/2016 11:36:15</date>
      </dates>
      <disabled />
    </piece>
    <piece id="18747">
      <classement>
        <version>
          <date>09/02/2016 11:37:06</date>
          <class>00001032</class>
          <rating>0</rating>
        </version>
      </classement>
      <disabled />
    </piece>
    <piece id="19112">
      <classement>
        <version>
          <date>09/02/2016 17:28:01</date>
          <class>00003243</class>
          <rating>0</rating>
        </version>
      </classement>
      <dates>
        <date>09/02/2016 17:28:46</date>
      </dates>
      <disabled />
    </piece>
    <piece id="19113">
      <classement>
        <version>
          <date>09/02/2016 17:48:10</date>
          <class>00002421</class>
          <rating>0</rating>
        </version>
      </classement>
      <disabled />
    </piece>
    <piece id="19305">
      <classement>
        <version>
          <date>09/02/2016 11:49:38</date>
          <class>00001114</class>
          <rating>0</rating>
        </version>
      </classement>
      <disabled />
    </piece>
    <piece id="19306">
      <classement>
        <version>
          <date>09/02/2016 11:50:40</date>
          <class>00001124</class>
          <rating>0</rating>
        </version>
      </classement>
      <disabled />
    </piece>
    <piece id="19307">
      <classement>
        <version>
          <date>09/02/2016 14:41:06</date>
          <class>00001202</class>
          <rating>0</rating>
        </version>
      </classement>
      <disabled />
    </piece>
    <piece id="19308">
      <classement>
        <version>
          <date>09/02/2016 17:20:35</date>
          <class>00001322</class>
          <rating>0</rating>
        </version>
      </classement>
      <disabled />
      <duration>133867</duration>
    </piece>
    <piece id="19334">
      <classement>
        <version>
          <date>09/02/2016 10:53:50</date>
          <class>00004133</class>
          <rating>0</rating>
        </version>
      </classement>
      <dates>
        <date>09/02/2016 10:55:56</date>
      </dates>
      <disabled />
    </piece>
    <piece id="19335">
      <classement>
        <version>
          <date>09/02/2016 17:59:41</date>
          <class>00003343</class>
          <rating>0</rating>
        </version>
      </classement>
      <disabled />
    </piece>
    <piece id="19336">
      <classement>
        <version>
          <date>09/02/2016 19:18:03</date>
          <class>0001035</class>
          <rating>0</rating>
        </version>
      </classement>
      <disabled />
    </piece>
    <piece id="19406">
      <classement>
        <version>
          <date>09/02/2016 17:30:36</date>
          <class>00005203</class>
          <rating>0</rating>
        </version>
      </classement>
      <dates>
        <date>09/02/2016 17:30:19</date>
      </dates>
      <disabled />
    </piece>
    <piece id="19532">
      <classement>
        <version>
          <date>09/02/2016 18:10:32</date>
          <class>00005301</class>
          <rating>0</rating>
        </version>
      </classement>
      <disabled />
    </piece>
    <piece id="19813">
      <classement>
        <version>
          <date>09/02/2016 18:13:15</date>
          <class>0001052</class>
          <rating>0</rating>
        </version>
      </classement>
      <disabled />
    </piece>
    <piece id="19814">
      <classement>
        <version>
          <date>09/02/2016 18:47:45</date>
          <class>0001112</class>
          <rating>0</rating>
        </version>
      </classement>
      <disabled />
    </piece>
    <piece id="20217">
      <classement>
        <version>
          <date>09/02/2016 11:04:23</date>
          <class>00002031</class>
          <rating>0</rating>
        </version>
      </classement>
      <dates>
        <date>09/02/2016 11:04:58</date>
      </dates>
      <disabled />
    </piece>
    <piece id="20218">
      <classement>
        <version>
          <date>09/02/2016 11:46:08</date>
          <class>00001224</class>
          <rating>0</rating>
        </version>
      </classement>
      <disabled />
    </piece>
    <piece id="20219">
      <classement>
        <version>
          <date>09/02/2016 11:48:27</date>
          <class>00002543</class>
          <rating>0</rating>
        </version>
      </classement>
      <disabled />
    </piece>
    <piece id="20250">
      <classement>
        <version>
          <date>09/02/2016 18:03:56</date>
          <class>00002353</class>
          <rating>0</rating>
        </version>
      </classement>
      <disabled />
    </piece>
    <piece id="20251">
      <classement>
        <version>
          <date>09/02/2016 18:07:25</date>
          <class>00001434</class>
          <rating>0</rating>
        </version>
      </classement>
      <disabled />
    </piece>
    <piece id="20375">
      <classement>
        <version>
          <date>09/02/2016 11:52:06</date>
          <class>00002101</class>
          <rating>0</rating>
        </version>
      </classement>
      <disabled />
    </piece>
    <piece id="20418">
      <classement>
        <version>
          <date>09/02/2016 18:54:28</date>
          <class>0001015</class>
          <rating>0</rating>
        </version>
      </classement>
      <disabled />
    </piece>
    <piece id="20782">
      <classement>
        <version>
          <date>09/02/2016 10:52:02</date>
          <class>00003533</class>
          <rating>0</rating>
        </version>
      </classement>
      <disabled />
    </piece>
    <piece id="20783">
      <classement>
        <version>
          <date>09/02/2016 17:44:47</date>
          <class>000005420</class>
          <rating>0</rating>
        </version>
      </classement>
      <disabled />
    </piece>
    <piece id="20784">
      <classement>
        <version>
          <date>09/02/2016 19:04:13</date>
          <class>0002003</class>
          <rating>0</rating>
        </version>
      </classement>
      <dates>
        <date>09/02/2016 19:02:32</date>
      </dates>
      <disabled />
    </piece>
    <piece id="21169">
      <classement>
        <version>
          <date>09/02/2016 11:00:07</date>
          <class>00001314</class>
          <rating>0</rating>
        </version>
      </classement>
      <disabled />
      <duration>321307</duration>
    </piece>
    <piece id="21170">
      <classement>
        <version>
          <date>09/02/2016 11:35:20</date>
          <class>00001152</class>
          <rating>0</rating>
        </version>
      </classement>
      <disabled />
      <duration>208120</duration>
    </piece>
    <piece id="21171">
      <classement>
        <version>
          <date>09/02/2016 11:47:20</date>
          <class>00001042</class>
          <rating>0</rating>
        </version>
      </classement>
      <disabled />
      <duration>223707</duration>
    </piece>
    <piece id="21172">
      <classement>
        <version>
          <date>09/02/2016 17:02:18</date>
          <class>00004433</class>
          <rating>0</rating>
        </version>
      </classement>
      <dates>
        <date>09/02/2016 17:02:42</date>
      </dates>
      <disabled />
      <duration>170227</duration>
    </piece>
    <piece id="21253">
      <classement>
        <version>
          <date>09/02/2016 10:57:44</date>
          <class>000002150</class>
          <rating>0</rating>
        </version>
      </classement>
      <dates>
        <date>09/02/2016 10:57:31</date>
      </dates>
      <disabled />
    </piece>
    <piece id="21254">
      <classement>
        <version>
          <date>09/02/2016 11:30:27</date>
          <class>00003313</class>
          <rating>0</rating>
        </version>
      </classement>
      <disabled />
    </piece>
    <piece id="21255">
      <classement>
        <version>
          <date>09/02/2016 11:33:52</date>
          <class>00003413</class>
          <rating>0</rating>
        </version>
      </classement>
      <disabled />
    </piece>
    <piece id="21667">
      <classement>
        <version>
          <date>09/02/2016 16:59:44</date>
          <class>0004240</class>
          <rating>0</rating>
        </version>
      </classement>
      <disabled />
    </piece>
    <piece id="21696">
      <classement>
        <version>
          <date>09/02/2016 17:47:17</date>
          <class>00001132</class>
          <rating>0</rating>
        </version>
      </classement>
      <disabled />
    </piece>
    <piece id="21763">
      <classement>
        <version>
          <date>09/02/2016 11:39:36</date>
          <class>00003513</class>
          <rating>0</rating>
        </version>
      </classement>
      <disabled />
    </piece>
    <piece id="21991">
      <classement>
        <version>
          <date>09/02/2016 18:57:54</date>
          <class>001041</class>
          <rating>0</rating>
        </version>
        <version>
          <date>09/02/2016 18:57:03</date>
          <class>01144</class>
          <rating>0</rating>
        </version>
      </classement>
      <disabled />
    </piece>
    <piece id="22207">
      <classement>
        <version>
          <date>09/02/2016 17:16:52</date>
          <class>00000405</class>
          <rating>0</rating>
        </version>
      </classement>
      <dates>
        <date>09/02/2016 17:16:33</date>
        <date>09/02/2016 17:15:39</date>
      </dates>
      <disabled />
    </piece>
    <piece id="22208">
      <classement>
        <version>
          <date>09/02/2016 17:34:35</date>
          <class>0002223</class>
          <rating>0</rating>
        </version>
      </classement>
      <disabled />
    </piece>
    <piece id="23009">
      <classement>
        <version>
          <date>09/02/2016 17:54:51</date>
          <class>0003203</class>
          <rating>0</rating>
        </version>
      </classement>
      <disabled />
    </piece>
    <piece id="23079">
      <classement>
        <version>
          <date>09/02/2016 17:39:54</date>
          <class>001202</class>
          <rating>0</rating>
        </version>
      </classement>
      <disabled />
    </piece>
    <piece id="23141">
      <classement>
        <version>
          <date>09/02/2016 17:58:00</date>
          <class>02034</class>
          <rating>0</rating>
        </version>
      </classement>
      <disabled />
    </piece>
    <piece id="23477">
      <classement>
        <version>
          <date>09/02/2016 14:47:40</date>
          <class>0003550</class>
          <rating>0</rating>
        </version>
      </classement>
      <disabled />
    </piece>
    <piece id="23535">
      <classement>
        <version>
          <date>09/02/2016 17:52:40</date>
          <class>00002011</class>
          <rating>0</rating>
        </version>
      </classement>
      <disabled />
    </piece>
    <piece id="23563">
      <classement>
        <version>
          <date>09/02/2016 11:32:24</date>
          <class>0002343</class>
          <rating>0</rating>
        </version>
      </classement>
      <disabled />
    </piece>
    <piece id="23578">
      <classement>
        <version>
          <date>09/02/2016 17:24:28</date>
          <class>00002253</class>
          <rating>0</rating>
        </version>
      </classement>
      <disabled />
    </piece>
    <piece id="23747">
      <classement>
        <version>
          <date>09/02/2016 18:02:15</date>
          <class>00002523</class>
          <rating>0</rating>
        </version>
      </classement>
      <dates>
        <date>09/02/2016 18:01:58</date>
      </dates>
      <disabled />
    </piece>
    <piece id="23748">
      <classement>
        <version>
          <date>09/02/2016 18:05:01</date>
          <class>000002250</class>
          <rating>0</rating>
        </version>
      </classement>
      <disabled />
    </piece>
    <piece id="23749">
      <classement>
        <version>
          <date>09/02/2016 18:05:52</date>
          <class>00001212</class>
          <rating>0</rating>
        </version>
      </classement>
      <disabled />
    </piece>
    <piece id="23750">
      <classement>
        <version>
          <date>09/02/2016 18:08:12</date>
          <class>000002450</class>
          <rating>0</rating>
        </version>
      </classement>
      <dates>
        <date>09/02/2016 18:07:59</date>
      </dates>
      <disabled />
    </piece>
    <piece id="23751">
      <classement>
        <version>
          <date>09/02/2016 18:11:41</date>
          <class>00001024</class>
          <rating>0</rating>
        </version>
      </classement>
      <disabled />
    </piece>
    <piece id="23752">
      <classement>
        <version>
          <date>09/02/2016 18:44:03</date>
          <class>00003023</class>
          <rating>0</rating>
        </version>
      </classement>
      <disabled />
    </piece>
    <piece id="23753">
      <classement>
        <version>
          <date>09/02/2016 18:51:25</date>
          <class>00004111</class>
          <rating>0</rating>
        </version>
      </classement>
      <disabled />
    </piece>
    <piece id="23754">
      <classement>
        <version>
          <date>09/02/2016 18:55:26</date>
          <class>000005520</class>
          <rating>0</rating>
        </version>
      </classement>
      <dates>
        <date>09/02/2016 18:55:09</date>
      </dates>
      <disabled />
    </piece>
    <piece id="23755">
      <classement>
        <version>
          <date>09/02/2016 19:12:14</date>
          <class>00005013</class>
          <rating>0</rating>
        </version>
      </classement>
      <disabled />
    </piece>
    <piece id="23992">
      <classement>
        <version>
          <date>09/02/2016 11:41:48</date>
          <class>0004050</class>
          <rating>0</rating>
        </version>
      </classement>
      <dates>
        <date>09/02/2016 11:41:30</date>
      </dates>
      <disabled />
    </piece>
    <piece id="24104">
      <classement>
        <version>
          <date>09/02/2016 11:09:54</date>
          <class>00004333</class>
          <rating>0</rating>
        </version>
      </classement>
      <disabled />
    </piece>
    <piece id="24706">
      <classement>
        <version>
          <date>09/02/2016 10:58:43</date>
          <class>000003020</class>
          <rating>0</rating>
        </version>
      </classement>
      <disabled />
    </piece>
    <piece id="24707">
      <classement>
        <version>
          <date>09/02/2016 11:23:25</date>
          <class>0000002110</class>
          <rating>0</rating>
        </version>
      </classement>
      <disabled />
    </piece>
    <piece id="24708">
      <classement>
        <version>
          <date>09/02/2016 11:27:21</date>
          <class>001022</class>
          <rating>0</rating>
        </version>
      </classement>
      <disabled />
    </piece>
    <piece id="28923">
      <classement>
        <version>
          <date>09/02/2016 14:38:17</date>
          <class>00004013</class>
          <rating>0</rating>
        </version>
      </classement>
      <disabled />
    </piece>
    <piece id="29172">
      <classement>
        <version>
          <date>09/02/2016 17:22:12</date>
          <class>00001543</class>
          <rating>0</rating>
        </version>
      </classement>
      <disabled />
    </piece>
    <piece id="29268">
      <classement>
        <version>
          <date>09/02/2016 17:38:13</date>
          <class>0002153</class>
          <rating>0</rating>
        </version>
      </classement>
      <disabled />
    </piece>
    <piece id="29269">
      <classement>
        <version>
          <date>09/02/2016 18:01:08</date>
          <class>0002513</class>
          <rating>0</rating>
        </version>
      </classement>
      <disabled />
    </piece>
    <piece id="29539">
      <classement>
        <version>
          <date>09/02/2016 11:25:44</date>
          <class>0002243</class>
          <rating>0</rating>
        </version>
      </classement>
      <disabled />
    </piece>
    <piece id="30045">
      <classement>
        <version>
          <date>09/02/2016 17:19:35</date>
          <class>0003013</class>
          <rating>0</rating>
        </version>
      </classement>
      <disabled />
    </piece>
    <piece id="30370">
      <classement>
        <version>
          <date>09/02/2016 11:11:40</date>
          <class>002043</class>
          <rating>0</rating>
        </version>
      </classement>
      <disabled />
    </piece>
    <piece id="30495">
      <classement>
        <version>
          <date>09/02/2016 11:44:51</date>
          <class>00001521</class>
          <rating>0</rating>
        </version>
      </classement>
      <disabled />
    </piece>
    <piece id="30496">
      <classement>
        <version>
          <date>09/02/2016 17:43:05</date>
          <class>00001344</class>
          <rating>0</rating>
        </version>
      </classement>
      <disabled />
    </piece>
    <piece id="30772">
      <classement>
        <version>
          <date>09/02/2016 11:18:14</date>
          <class>000004240</class>
          <rating>0</rating>
        </version>
      </classement>
      <disabled />
    </piece>
    <piece id="30773">
      <classement>
        <version>
          <date>09/02/2016 11:20:06</date>
          <class>000003150</class>
          <rating>0</rating>
        </version>
      </classement>
      <disabled />
    </piece>
    <piece id="30774">
      <classement>
        <version>
          <date>09/02/2016 18:46:29</date>
          <class>00001302</class>
          <rating>0</rating>
        </version>
      </classement>
      <disabled />
    </piece>
    <piece id="30775">
      <classement>
        <version>
          <date>09/02/2016 18:49:10</date>
          <class>00005550</class>
          <rating>0</rating>
        </version>
      </classement>
      <disabled />
    </piece>
    <piece id="30776">
      <classement>
        <version>
          <date>09/02/2016 19:15:21</date>
          <class>0001025</class>
          <rating>0</rating>
        </version>
      </classement>
      <disabled />
    </piece>
    <piece id="30914">
      <classement>
        <version>
          <date>09/02/2016 11:53:20</date>
          <class>00002321</class>
          <rating>0</rating>
        </version>
      </classement>
      <disabled />
    </piece>
    <piece id="30915">
      <classement>
        <version>
          <date>09/02/2016 17:50:34</date>
          <class>000004150</class>
          <rating>0</rating>
        </version>
      </classement>
      <disabled />
    </piece>
  </pieces>
</db>
