<?xml version="1.0" encoding="utf-8"?>
<db version="3" seq_piece="34020">
  <pieces>
    <piece id="1500">
      <classement>
        <version date="30/09/2016 17:31:58" value="0004.1" />
      </classement>
      <duration>136490</duration>
    </piece>
    <piece id="1577">
      <classement>
        <version date="30/09/2016 16:55:52" value="0003315.1" />
      </classement>
      <dates>
        <date>30/09/2016 16:54:36</date>
      </dates>
      <disabled />
    </piece>
    <piece id="3219">
      <classement>
        <version date="30/09/2016 11:11:24" value="0004.3" />
      </classement>
    </piece>
    <piece id="5157">
      <classement>
        <version date="30/09/2016 14:58:20" value="0004.3" />
      </classement>
      <duration>206894</duration>
    </piece>
    <piece id="9308">
      <classement>
        <version date="30/09/2016 14:56:08" value="0004004.0" />
      </classement>
      <disabled />
    </piece>
    <piece id="9328">
      <classement>
        <version date="30/09/2016 16:13:51" value="0003.5" />
      </classement>
    </piece>
    <piece id="9350">
      <classement>
        <version date="30/09/2016 16:17:02" value="0004034.0" />
      </classement>
      <disabled />
      <duration>450406</duration>
    </piece>
    <piece id="10907">
      <classement>
        <version date="30/09/2016 11:24:17" value="030.1" />
      </classement>
      <dates>
        <date>30/09/2016 11:20:33</date>
      </dates>
    </piece>
    <piece id="10972">
      <classement>
        <version date="30/09/2016 10:15:18" value="103.1" />
      </classement>
    </piece>
    <piece id="12740">
      <classement>
        <version date="30/09/2016 17:17:44" value="015.4" />
      </classement>
    </piece>
    <piece id="12777">
      <classement>
        <version date="30/09/2016 16:33:42" value="040.4" />
      </classement>
      <duration>354801</duration>
    </piece>
    <piece id="13050">
      <classement>
        <version date="30/09/2016 16:24:25" value="003.3" />
      </classement>
      <duration>236693</duration>
    </piece>
    <piece id="13051">
      <classement>
        <version date="30/09/2016 17:19:14" value="021.3" />
      </classement>
      <duration>238800</duration>
    </piece>
    <piece id="14153">
      <classement>
        <version date="30/09/2016 16:12:25" value="002.4" />
      </classement>
    </piece>
    <piece id="14154">
      <classement>
        <version date="30/09/2016 17:08:41" value="020.3" />
      </classement>
    </piece>
    <piece id="14310">
      <classement>
        <version date="30/09/2016 15:00:12" value="012.2" />
      </classement>
      <duration>225800</duration>
    </piece>
    <piece id="14311">
      <duration>225800</duration>
    </piece>
    <piece id="14644">
      <classement>
        <version date="30/09/2016 17:13:13" value="0010.2" />
      </classement>
    </piece>
    <piece id="15313">
      <classement>
        <version date="30/09/2016 18:10:20" value="025.4" />
      </classement>
    </piece>
    <piece id="15570">
      <classement>
        <version date="30/09/2016 17:33:51" value="022.3" />
      </classement>
    </piece>
    <piece id="15610">
      <classement>
        <version date="30/09/2016 10:21:06" value="043.2" />
      </classement>
    </piece>
    <piece id="15802">
      <classement>
        <version date="30/09/2016 17:07:48" value="0003503.1" />
      </classement>
      <disabled />
    </piece>
    <piece id="15811">
      <classement>
        <version date="30/09/2016 16:09:48" value="0004.3" />
      </classement>
    </piece>
    <piece id="16395">
      <classement>
        <version date="30/09/2016 11:05:39" value="0005.1" />
      </classement>
    </piece>
    <piece id="16659">
      <classement>
        <version date="30/09/2016 16:35:04" value="015.1" />
      </classement>
    </piece>
    <piece id="17036">
      <classement>
        <version date="30/09/2016 17:34:30" value="0004.4" />
      </classement>
    </piece>
    <piece id="17119">
      <classement>
        <version date="30/09/2016 17:20:14" value="0004.5" />
      </classement>
    </piece>
    <piece id="17234">
      <classement>
        <version date="30/09/2016 16:22:39" value="0004.5" />
      </classement>
    </piece>
    <piece id="17279">
      <classement>
        <version date="30/09/2016 17:37:37" value="0004.4" />
      </classement>
    </piece>
    <piece id="17470">
      <classement>
        <version date="30/09/2016 16:05:41" value="0014.1" />
      </classement>
      <duration>277800</duration>
    </piece>
    <piece id="17486">
      <classement>
        <version date="30/09/2016 17:04:05" value="032.1" />
      </classement>
      <duration>263867</duration>
    </piece>
    <piece id="17622">
      <classement>
        <version date="30/09/2016 11:48:24" value="003.1" />
      </classement>
      <dates>
        <date>30/09/2016 11:43:30</date>
      </dates>
    </piece>
    <piece id="17623">
      <dates>
        <date>30/09/2016 11:46:20</date>
      </dates>
    </piece>
    <piece id="18586">
      <classement>
        <version date="30/09/2016 11:09:15" value="0011.2" />
      </classement>
    </piece>
    <piece id="18944">
      <classement>
        <version date="30/09/2016 17:11:50" value="0040.4" />
      </classement>
    </piece>
    <piece id="18955">
      <classement>
        <version date="30/09/2016 16:31:26" value="0003423.1" />
      </classement>
      <disabled />
    </piece>
    <piece id="19157">
      <classement>
        <version date="30/09/2016 17:28:55" value="0003335.1" />
      </classement>
      <disabled />
    </piece>
    <piece id="19223">
      <classement>
        <version date="30/09/2016 16:36:49" value="0003055.1" />
      </classement>
      <disabled />
    </piece>
    <piece id="19224">
      <classement>
        <version date="30/09/2016 17:30:09" value="0002153.2" />
      </classement>
      <disabled />
    </piece>
    <piece id="19493">
      <classement>
        <version date="30/09/2016 16:58:55" value="0003355.1" />
      </classement>
      <dates>
        <date>30/09/2016 16:58:55</date>
      </dates>
      <disabled />
    </piece>
    <piece id="20100">
      <classement>
        <version date="30/09/2016 16:08:31" value="0105.1" />
      </classement>
    </piece>
    <piece id="20475">
      <classement>
        <version date="30/09/2016 16:39:29" value="023.1" />
      </classement>
      <duration>277032</duration>
    </piece>
    <piece id="20583">
      <classement>
        <version date="30/09/2016 11:16:04" value="0005.0" />
      </classement>
      <duration>192427</duration>
    </piece>
    <piece id="21323">
      <classement>
        <version date="30/09/2016 17:15:35" value="0003.4" />
      </classement>
    </piece>
    <piece id="21749">
      <classement>
        <version date="30/09/2016 16:21:16" value="0004.5" />
      </classement>
      <duration>253067</duration>
    </piece>
    <piece id="22019">
      <classement>
        <version date="30/09/2016 17:25:57" value="0010.0" />
      </classement>
      <dates>
        <date>30/09/2016 17:23:09</date>
      </dates>
    </piece>
    <piece id="22403">
      <classement>
        <version date="30/09/2016 16:49:56" value="0100.2" />
      </classement>
    </piece>
    <piece id="22431">
      <classement>
        <version date="30/09/2016 17:00:30" value="0020.2" />
      </classement>
    </piece>
    <piece id="22937">
      <classement>
        <version date="30/09/2016 11:54:58" value="014.1" />
      </classement>
      <duration>289293</duration>
    </piece>
    <piece id="23383">
      <classement>
        <version date="30/09/2016 17:35:02" value="0005.1" />
      </classement>
    </piece>
    <piece id="23699">
      <classement>
        <version date="30/09/2016 17:02:12" value="0004.2" />
      </classement>
    </piece>
    <piece id="23909">
      <classement>
        <version date="30/09/2016 18:08:13" value="020.2" />
      </classement>
    </piece>
    <piece id="23991">
      <classement>
        <version date="30/09/2016 11:37:49" value="0011.3" />
      </classement>
      <dates>
        <date>30/09/2016 11:36:49</date>
      </dates>
    </piece>
    <piece id="24098">
      <classement>
        <version date="30/09/2016 10:22:21" value="0005.0" />
      </classement>
      <dates>
        <date>30/09/2016 10:22:23</date>
      </dates>
    </piece>
    <piece id="25002">
      <classement>
        <version date="30/09/2016 11:52:01" value="25.1" />
      </classement>
      <dates>
        <date>30/09/2016 11:51:46</date>
      </dates>
    </piece>
    <piece id="25924">
      <classement>
        <version date="30/09/2016 11:10:01" value="0010.1" />
      </classement>
    </piece>
    <piece id="26763">
      <classement>
        <version date="30/09/2016 17:28:03" value="115.1" />
      </classement>
    </piece>
    <piece id="27000">
      <classement>
        <version date="30/09/2016 14:53:05" value="0020.4" />
      </classement>
      <dates>
        <date>30/09/2016 14:44:03</date>
        <date>30/09/2016 12:00:24</date>
      </dates>
    </piece>
    <piece id="27001">
      <dates>
        <date>30/09/2016 14:47:29</date>
        <date>30/09/2016 12:03:49</date>
      </dates>
    </piece>
    <piece id="27002">
      <dates>
        <date>30/09/2016 14:49:06</date>
      </dates>
      <duration>97283</duration>
    </piece>
    <piece id="27003">
      <duration>392808</duration>
    </piece>
    <piece id="27411">
      <classement>
        <version date="30/09/2016 16:19:37" value="003.2" />
      </classement>
      <duration>870876</duration>
    </piece>
    <piece id="27625">
      <classement>
        <version date="30/09/2016 17:10:21" value="0005.5" />
      </classement>
    </piece>
    <piece id="29984">
      <classement>
        <version date="30/09/2016 17:06:14" value="0003.5" />
      </classement>
    </piece>
    <piece id="30767">
      <classement>
        <version date="30/09/2016 11:13:07" value="0003545.0" />
      </classement>
      <disabled />
    </piece>
    <piece id="31718">
      <classement>
        <version date="30/09/2016 11:31:02" value="20.1" />
      </classement>
      <dates>
        <date>30/09/2016 11:30:53</date>
        <date>30/09/2016 11:26:40</date>
      </dates>
    </piece>
    <piece id="31719">
      <dates>
        <date>30/09/2016 11:33:27</date>
      </dates>
    </piece>
    <piece id="32581">
      <classement>
        <version date="30/09/2016 11:14:36" value="0001232.4" />
      </classement>
      <disabled />
    </piece>
    <piece id="33690">
      <classement>
        <version date="30/09/2016 18:09:17" value="0003453.3" />
      </classement>
      <disabled />
    </piece>
    <piece id="33787">
      <classement>
        <version date="30/09/2016 16:26:04" value="00034.3" />
      </classement>
    </piece>
    <piece id="33849">
      <classement>
        <version date="30/09/2016 18:11:33" value="00041.2" />
      </classement>
    </piece>
  </pieces>
</db>
